Metadata-Version: 2.1
Name: pypiolegg
Version: 0.1
Summary: A Hello World package
Home-page: https://https://github.com/olegnechaev1/github/tree/dev/task12
Author: Oleg Nechaev
Author-email: nechaev20000@gmail.com
License: MIT
Platform: UNKNOWN
